odoo10_addon_test_shopinvader_payment-10.0.2.0.0.99.dev4-py3.8-nspkg.pth
odoo/addons/test_shopinvader_payment/README.rst
odoo/addons/test_shopinvader_payment/__init__.py
odoo/addons/test_shopinvader_payment/__manifest__.py
odoo/addons/test_shopinvader_payment/i18n/test_shopinvader_payment.pot
odoo/addons/test_shopinvader_payment/readme/CONTRIBUTORS.rst
odoo/addons/test_shopinvader_payment/readme/DESCRIPTION.rst
odoo/addons/test_shopinvader_payment/static/description/index.html
odoo/addons/test_shopinvader_payment/tests/__init__.py
odoo/addons/test_shopinvader_payment/tests/test_shopinvader_payment_manual.py
odoo/addons/test_shopinvader_payment/tests/test_shopinvader_quotation_payment.py
odoo10_addon_test_shopinvader_payment-10.0.2.0.0.99.dev4.dist-info/METADATA
odoo10_addon_test_shopinvader_payment-10.0.2.0.0.99.dev4.dist-info/WHEEL
odoo10_addon_test_shopinvader_payment-10.0.2.0.0.99.dev4.dist-info/namespace_packages.txt
odoo10_addon_test_shopinvader_payment-10.0.2.0.0.99.dev4.dist-info/top_level.txt
odoo10_addon_test_shopinvader_payment-10.0.2.0.0.99.dev4.dist-info/RECORD
